<?xml version="1.0" encoding="UTF-8" ?>
<!DOCTYPE mapper PUBLIC "-//mybatis.org//DTD Mapper 3.0//EN" "http://mybatis.org/dtd/mybatis-3-mapper.dtd" >
<mapper namespace="com.comdosoft.financial.manage.mapper.zhangfu.PrepareGoodRecordMapper" >
  <resultMap id="BaseResultMap" type="com.comdosoft.financial.manage.domain.zhangfu.PrepareGoodRecord" >
    <!--
      WARNING - @mbggenerated
      This element is automatically generated by MyBatis Generator, do not modify.
      This element was generated on Thu Jan 29 14:22:32 CST 2015.
    -->
    <id column="id" property="id" jdbcType="INTEGER" />
    <result column="agent_id" property="agentId" jdbcType="INTEGER" />
    <result column="good_id" property="goodId" jdbcType="INTEGER" />
    <result column="quantity" property="quantity" jdbcType="INTEGER" />
    <result column="created_at" property="createdAt" jdbcType="TIMESTAMP" />
    <result column="updated_at" property="updatedAt" jdbcType="TIMESTAMP" />
    <result column="process_user_id" property="processUserId" jdbcType="INTEGER" />
    <result column="pay_channel_id" property="payChannelId" jdbcType="INTEGER" />
  </resultMap>
  <resultMap id="ResultMapWithBLOBs" type="com.comdosoft.financial.manage.domain.zhangfu.PrepareGoodRecord" extends="BaseResultMap" >
    <!--
      WARNING - @mbggenerated
      This element is automatically generated by MyBatis Generator, do not modify.
      This element was generated on Thu Jan 29 14:22:32 CST 2015.
    -->
    <result column="terminal_list" property="terminalList" jdbcType="LONGVARCHAR" />
  </resultMap>
  <sql id="Base_Column_List" >
    <!--
      WARNING - @mbggenerated
      This element is automatically generated by MyBatis Generator, do not modify.
      This element was generated on Thu Jan 29 14:22:32 CST 2015.
    -->
    id, agent_id, good_id, quantity, created_at, updated_at, process_user_id, pay_channel_id
  </sql>
  <sql id="Blob_Column_List" >
    <!--
      WARNING - @mbggenerated
      This element is automatically generated by MyBatis Generator, do not modify.
      This element was generated on Thu Jan 29 14:22:32 CST 2015.
    -->
    terminal_list
  </sql>
  <select id="selectByPrimaryKey" resultMap="ResultMapWithBLOBs" parameterType="java.lang.Integer" >
    <!--
      WARNING - @mbggenerated
      This element is automatically generated by MyBatis Generator, do not modify.
      This element was generated on Thu Jan 29 14:22:32 CST 2015.
    -->
    select 
    <include refid="Base_Column_List" />
    ,
    <include refid="Blob_Column_List" />
    from prepare_goods_records
    where id = #{id,jdbcType=INTEGER}
  </select>
  <delete id="deleteByPrimaryKey" parameterType="java.lang.Integer" >
    <!--
      WARNING - @mbggenerated
      This element is automatically generated by MyBatis Generator, do not modify.
      This element was generated on Thu Jan 29 14:22:32 CST 2015.
    -->
    delete from prepare_goods_records
    where id = #{id,jdbcType=INTEGER}
  </delete>
  <insert id="insert" parameterType="com.comdosoft.financial.manage.domain.zhangfu.PrepareGoodRecord" >
    <!--
      WARNING - @mbggenerated
      This element is automatically generated by MyBatis Generator, do not modify.
      This element was generated on Thu Jan 29 14:22:32 CST 2015.
    -->
    insert into prepare_goods_records (id, agent_id, good_id, 
      quantity, created_at, updated_at, 
      process_user_id, pay_channel_id, terminal_list
      )
    values (#{id,jdbcType=INTEGER}, #{agentId,jdbcType=INTEGER}, #{goodId,jdbcType=INTEGER}, 
      #{quantity,jdbcType=INTEGER}, #{createdAt,jdbcType=TIMESTAMP}, #{updatedAt,jdbcType=TIMESTAMP}, 
      #{processUserId,jdbcType=INTEGER}, #{payChannelId,jdbcType=INTEGER}, #{terminalList,jdbcType=LONGVARCHAR}
      )
  </insert>
  <insert id="insertSelective" parameterType="com.comdosoft.financial.manage.domain.zhangfu.PrepareGoodRecord" >
    <!--
      WARNING - @mbggenerated
      This element is automatically generated by MyBatis Generator, do not modify.
      This element was generated on Thu Jan 29 14:22:32 CST 2015.
    -->
    insert into prepare_goods_records
    <trim prefix="(" suffix=")" suffixOverrides="," >
      <if test="id != null" >
        id,
      </if>
      <if test="agentId != null" >
        agent_id,
      </if>
      <if test="goodId != null" >
        good_id,
      </if>
      <if test="quantity != null" >
        quantity,
      </if>
      <if test="createdAt != null" >
        created_at,
      </if>
      <if test="updatedAt != null" >
        updated_at,
      </if>
      <if test="processUserId != null" >
        process_user_id,
      </if>
      <if test="payChannelId != null" >
        pay_channel_id,
      </if>
      <if test="terminalList != null" >
        terminal_list,
      </if>
    </trim>
    <trim prefix="values (" suffix=")" suffixOverrides="," >
      <if test="id != null" >
        #{id,jdbcType=INTEGER},
      </if>
      <if test="agentId != null" >
        #{agentId,jdbcType=INTEGER},
      </if>
      <if test="goodId != null" >
        #{goodId,jdbcType=INTEGER},
      </if>
      <if test="quantity != null" >
        #{quantity,jdbcType=INTEGER},
      </if>
      <if test="createdAt != null" >
        #{createdAt,jdbcType=TIMESTAMP},
      </if>
      <if test="updatedAt != null" >
        #{updatedAt,jdbcType=TIMESTAMP},
      </if>
      <if test="processUserId != null" >
        #{processUserId,jdbcType=INTEGER},
      </if>
      <if test="payChannelId != null" >
        #{payChannelId,jdbcType=INTEGER},
      </if>
      <if test="terminalList != null" >
        #{terminalList,jdbcType=LONGVARCHAR},
      </if>
    </trim>
  </insert>
  <update id="updateByPrimaryKeySelective" parameterType="com.comdosoft.financial.manage.domain.zhangfu.PrepareGoodRecord" >
    <!--
      WARNING - @mbggenerated
      This element is automatically generated by MyBatis Generator, do not modify.
      This element was generated on Thu Jan 29 14:22:32 CST 2015.
    -->
    update prepare_goods_records
    <set >
      <if test="agentId != null" >
        agent_id = #{agentId,jdbcType=INTEGER},
      </if>
      <if test="goodId != null" >
        good_id = #{goodId,jdbcType=INTEGER},
      </if>
      <if test="quantity != null" >
        quantity = #{quantity,jdbcType=INTEGER},
      </if>
      <if test="createdAt != null" >
        created_at = #{createdAt,jdbcType=TIMESTAMP},
      </if>
      <if test="updatedAt != null" >
        updated_at = #{updatedAt,jdbcType=TIMESTAMP},
      </if>
      <if test="processUserId != null" >
        process_user_id = #{processUserId,jdbcType=INTEGER},
      </if>
      <if test="payChannelId != null" >
        pay_channel_id = #{payChannelId,jdbcType=INTEGER},
      </if>
      <if test="terminalList != null" >
        terminal_list = #{terminalList,jdbcType=LONGVARCHAR},
      </if>
    </set>
    where id = #{id,jdbcType=INTEGER}
  </update>
  <update id="updateByPrimaryKeyWithBLOBs" parameterType="com.comdosoft.financial.manage.domain.zhangfu.PrepareGoodRecord" >
    <!--
      WARNING - @mbggenerated
      This element is automatically generated by MyBatis Generator, do not modify.
      This element was generated on Thu Jan 29 14:22:32 CST 2015.
    -->
    update prepare_goods_records
    set agent_id = #{agentId,jdbcType=INTEGER},
      good_id = #{goodId,jdbcType=INTEGER},
      quantity = #{quantity,jdbcType=INTEGER},
      created_at = #{createdAt,jdbcType=TIMESTAMP},
      updated_at = #{updatedAt,jdbcType=TIMESTAMP},
      process_user_id = #{processUserId,jdbcType=INTEGER},
      pay_channel_id = #{payChannelId,jdbcType=INTEGER},
      terminal_list = #{terminalList,jdbcType=LONGVARCHAR}
    where id = #{id,jdbcType=INTEGER}
  </update>
  <update id="updateByPrimaryKey" parameterType="com.comdosoft.financial.manage.domain.zhangfu.PrepareGoodRecord" >
    <!--
      WARNING - @mbggenerated
      This element is automatically generated by MyBatis Generator, do not modify.
      This element was generated on Thu Jan 29 14:22:32 CST 2015.
    -->
    update prepare_goods_records
    set agent_id = #{agentId,jdbcType=INTEGER},
      good_id = #{goodId,jdbcType=INTEGER},
      quantity = #{quantity,jdbcType=INTEGER},
      created_at = #{createdAt,jdbcType=TIMESTAMP},
      updated_at = #{updatedAt,jdbcType=TIMESTAMP},
      process_user_id = #{processUserId,jdbcType=INTEGER},
      pay_channel_id = #{payChannelId,jdbcType=INTEGER}
    where id = #{id,jdbcType=INTEGER}
  </update>
</mapper>