<?xml version="1.0" encoding="UTF-8" ?>
<!DOCTYPE mapper PUBLIC "-//mybatis.org//DTD Mapper 3.0//EN" "http://mybatis.org/dtd/mybatis-3-mapper.dtd" >
<mapper namespace="com.comdosoft.financial.manage.mapper.zhangfu.TerminalMapper" >
  <resultMap id="BaseResultMap" type="com.comdosoft.financial.manage.domain.zhangfu.Terminal" >
    <!--
      WARNING - @mbggenerated
      This element is automatically generated by MyBatis Generator, do not modify.
      This element was generated on Thu Jan 29 14:34:31 CST 2015.
    -->
    <id column="id" property="id" jdbcType="INTEGER" />
    <result column="good_id" property="goodId" jdbcType="INTEGER" />
    <result column="serial_num" property="serialNum" jdbcType="VARCHAR" />
    <result column="pay_channel_id" property="payChannelId" jdbcType="INTEGER" />
    <result column="merchant_id" property="merchantId" jdbcType="INTEGER" />
    <result column="customer_id" property="customerId" jdbcType="INTEGER" />
    <result column="status" property="status" jdbcType="TINYINT" />
    <result column="agent_id" property="agentId" jdbcType="INTEGER" />
    <result column="order_id" property="orderId" jdbcType="INTEGER" />
    <result column="account" property="account" jdbcType="VARCHAR" />
    <result column="password" property="password" jdbcType="VARCHAR" />
    <result column="is_return_cs_depots" property="isReturnCsDepots" jdbcType="BIT" />
    <result column="created_at" property="createdAt" jdbcType="TIMESTAMP" />
    <result column="updated_at" property="updatedAt" jdbcType="TIMESTAMP" />
    <result column="type" property="type" jdbcType="TINYINT" />
    <result column="merchant_num" property="merchantNum" jdbcType="VARCHAR" />
    <result column="is_rate_wrong" property="isRateWrong" jdbcType="BIT" />
    <result column="base_rate" property="baseRate" jdbcType="INTEGER" />
    <result column="terminal_marks_id" property="terminalMarksId" jdbcType="INTEGER" />
    <result column="billing_cycles_id" property="billingCyclesId" jdbcType="INTEGER" />
  </resultMap>
  <resultMap id="ResultMapWithBLOBs" type="com.comdosoft.financial.manage.domain.zhangfu.Terminal" extends="BaseResultMap" >
    <!--
      WARNING - @mbggenerated
      This element is automatically generated by MyBatis Generator, do not modify.
      This element was generated on Thu Jan 29 14:34:31 CST 2015.
    -->
    <result column="mark_xml" property="markXml" jdbcType="LONGVARCHAR" />
  </resultMap>
  <sql id="Base_Column_List" >
    <!--
      WARNING - @mbggenerated
      This element is automatically generated by MyBatis Generator, do not modify.
      This element was generated on Thu Jan 29 14:34:31 CST 2015.
    -->
    id, good_id, serial_num, pay_channel_id, merchant_id, customer_id, status, agent_id, 
    order_id, account, password, is_return_cs_depots, created_at, updated_at, type, merchant_num, 
    is_rate_wrong, base_rate, terminal_marks_id, billing_cycles_id
  </sql>
  <sql id="Blob_Column_List" >
    <!--
      WARNING - @mbggenerated
      This element is automatically generated by MyBatis Generator, do not modify.
      This element was generated on Thu Jan 29 14:34:31 CST 2015.
    -->
    mark_xml
  </sql>
  <select id="selectByPrimaryKey" resultMap="ResultMapWithBLOBs" parameterType="java.lang.Integer" >
    <!--
      WARNING - @mbggenerated
      This element is automatically generated by MyBatis Generator, do not modify.
      This element was generated on Thu Jan 29 14:34:31 CST 2015.
    -->
    select 
    <include refid="Base_Column_List" />
    ,
    <include refid="Blob_Column_List" />
    from terminals
    where id = #{id,jdbcType=INTEGER}
  </select>
  <delete id="deleteByPrimaryKey" parameterType="java.lang.Integer" >
    <!--
      WARNING - @mbggenerated
      This element is automatically generated by MyBatis Generator, do not modify.
      This element was generated on Thu Jan 29 14:34:31 CST 2015.
    -->
    delete from terminals
    where id = #{id,jdbcType=INTEGER}
  </delete>
  <insert id="insert" parameterType="com.comdosoft.financial.manage.domain.zhangfu.Terminal" >
    <!--
      WARNING - @mbggenerated
      This element is automatically generated by MyBatis Generator, do not modify.
      This element was generated on Thu Jan 29 14:34:31 CST 2015.
    -->
    insert into terminals (id, good_id, serial_num, 
      pay_channel_id, merchant_id, customer_id, 
      status, agent_id, order_id, 
      account, password, is_return_cs_depots, 
      created_at, updated_at, type, 
      merchant_num, is_rate_wrong, base_rate, 
      terminal_marks_id, billing_cycles_id, mark_xml
      )
    values (#{id,jdbcType=INTEGER}, #{goodId,jdbcType=INTEGER}, #{serialNum,jdbcType=VARCHAR}, 
      #{payChannelId,jdbcType=INTEGER}, #{merchantId,jdbcType=INTEGER}, #{customerId,jdbcType=INTEGER}, 
      #{status,jdbcType=TINYINT}, #{agentId,jdbcType=INTEGER}, #{orderId,jdbcType=INTEGER}, 
      #{account,jdbcType=VARCHAR}, #{password,jdbcType=VARCHAR}, #{isReturnCsDepots,jdbcType=BIT}, 
      #{createdAt,jdbcType=TIMESTAMP}, #{updatedAt,jdbcType=TIMESTAMP}, #{type,jdbcType=TINYINT}, 
      #{merchantNum,jdbcType=VARCHAR}, #{isRateWrong,jdbcType=BIT}, #{baseRate,jdbcType=INTEGER}, 
      #{terminalMarksId,jdbcType=INTEGER}, #{billingCyclesId,jdbcType=INTEGER}, #{markXml,jdbcType=LONGVARCHAR}
      )
  </insert>
  <insert id="insertSelective" parameterType="com.comdosoft.financial.manage.domain.zhangfu.Terminal" >
    <!--
      WARNING - @mbggenerated
      This element is automatically generated by MyBatis Generator, do not modify.
      This element was generated on Thu Jan 29 14:34:31 CST 2015.
    -->
    insert into terminals
    <trim prefix="(" suffix=")" suffixOverrides="," >
      <if test="id != null" >
        id,
      </if>
      <if test="goodId != null" >
        good_id,
      </if>
      <if test="serialNum != null" >
        serial_num,
      </if>
      <if test="payChannelId != null" >
        pay_channel_id,
      </if>
      <if test="merchantId != null" >
        merchant_id,
      </if>
      <if test="customerId != null" >
        customer_id,
      </if>
      <if test="status != null" >
        status,
      </if>
      <if test="agentId != null" >
        agent_id,
      </if>
      <if test="orderId != null" >
        order_id,
      </if>
      <if test="account != null" >
        account,
      </if>
      <if test="password != null" >
        password,
      </if>
      <if test="isReturnCsDepots != null" >
        is_return_cs_depots,
      </if>
      <if test="createdAt != null" >
        created_at,
      </if>
      <if test="updatedAt != null" >
        updated_at,
      </if>
      <if test="type != null" >
        type,
      </if>
      <if test="merchantNum != null" >
        merchant_num,
      </if>
      <if test="isRateWrong != null" >
        is_rate_wrong,
      </if>
      <if test="baseRate != null" >
        base_rate,
      </if>
      <if test="terminalMarksId != null" >
        terminal_marks_id,
      </if>
      <if test="billingCyclesId != null" >
        billing_cycles_id,
      </if>
      <if test="markXml != null" >
        mark_xml,
      </if>
    </trim>
    <trim prefix="values (" suffix=")" suffixOverrides="," >
      <if test="id != null" >
        #{id,jdbcType=INTEGER},
      </if>
      <if test="goodId != null" >
        #{goodId,jdbcType=INTEGER},
      </if>
      <if test="serialNum != null" >
        #{serialNum,jdbcType=VARCHAR},
      </if>
      <if test="payChannelId != null" >
        #{payChannelId,jdbcType=INTEGER},
      </if>
      <if test="merchantId != null" >
        #{merchantId,jdbcType=INTEGER},
      </if>
      <if test="customerId != null" >
        #{customerId,jdbcType=INTEGER},
      </if>
      <if test="status != null" >
        #{status,jdbcType=TINYINT},
      </if>
      <if test="agentId != null" >
        #{agentId,jdbcType=INTEGER},
      </if>
      <if test="orderId != null" >
        #{orderId,jdbcType=INTEGER},
      </if>
      <if test="account != null" >
        #{account,jdbcType=VARCHAR},
      </if>
      <if test="password != null" >
        #{password,jdbcType=VARCHAR},
      </if>
      <if test="isReturnCsDepots != null" >
        #{isReturnCsDepots,jdbcType=BIT},
      </if>
      <if test="createdAt != null" >
        #{createdAt,jdbcType=TIMESTAMP},
      </if>
      <if test="updatedAt != null" >
        #{updatedAt,jdbcType=TIMESTAMP},
      </if>
      <if test="type != null" >
        #{type,jdbcType=TINYINT},
      </if>
      <if test="merchantNum != null" >
        #{merchantNum,jdbcType=VARCHAR},
      </if>
      <if test="isRateWrong != null" >
        #{isRateWrong,jdbcType=BIT},
      </if>
      <if test="baseRate != null" >
        #{baseRate,jdbcType=INTEGER},
      </if>
      <if test="terminalMarksId != null" >
        #{terminalMarksId,jdbcType=INTEGER},
      </if>
      <if test="billingCyclesId != null" >
        #{billingCyclesId,jdbcType=INTEGER},
      </if>
      <if test="markXml != null" >
        #{markXml,jdbcType=LONGVARCHAR},
      </if>
    </trim>
  </insert>
  <update id="updateByPrimaryKeySelective" parameterType="com.comdosoft.financial.manage.domain.zhangfu.Terminal" >
    <!--
      WARNING - @mbggenerated
      This element is automatically generated by MyBatis Generator, do not modify.
      This element was generated on Thu Jan 29 14:34:31 CST 2015.
    -->
    update terminals
    <set >
      <if test="goodId != null" >
        good_id = #{goodId,jdbcType=INTEGER},
      </if>
      <if test="serialNum != null" >
        serial_num = #{serialNum,jdbcType=VARCHAR},
      </if>
      <if test="payChannelId != null" >
        pay_channel_id = #{payChannelId,jdbcType=INTEGER},
      </if>
      <if test="merchantId != null" >
        merchant_id = #{merchantId,jdbcType=INTEGER},
      </if>
      <if test="customerId != null" >
        customer_id = #{customerId,jdbcType=INTEGER},
      </if>
      <if test="status != null" >
        status = #{status,jdbcType=TINYINT},
      </if>
      <if test="agentId != null" >
        agent_id = #{agentId,jdbcType=INTEGER},
      </if>
      <if test="orderId != null" >
        order_id = #{orderId,jdbcType=INTEGER},
      </if>
      <if test="account != null" >
        account = #{account,jdbcType=VARCHAR},
      </if>
      <if test="password != null" >
        password = #{password,jdbcType=VARCHAR},
      </if>
      <if test="isReturnCsDepots != null" >
        is_return_cs_depots = #{isReturnCsDepots,jdbcType=BIT},
      </if>
      <if test="createdAt != null" >
        created_at = #{createdAt,jdbcType=TIMESTAMP},
      </if>
      <if test="updatedAt != null" >
        updated_at = #{updatedAt,jdbcType=TIMESTAMP},
      </if>
      <if test="type != null" >
        type = #{type,jdbcType=TINYINT},
      </if>
      <if test="merchantNum != null" >
        merchant_num = #{merchantNum,jdbcType=VARCHAR},
      </if>
      <if test="isRateWrong != null" >
        is_rate_wrong = #{isRateWrong,jdbcType=BIT},
      </if>
      <if test="baseRate != null" >
        base_rate = #{baseRate,jdbcType=INTEGER},
      </if>
      <if test="terminalMarksId != null" >
        terminal_marks_id = #{terminalMarksId,jdbcType=INTEGER},
      </if>
      <if test="billingCyclesId != null" >
        billing_cycles_id = #{billingCyclesId,jdbcType=INTEGER},
      </if>
      <if test="markXml != null" >
        mark_xml = #{markXml,jdbcType=LONGVARCHAR},
      </if>
    </set>
    where id = #{id,jdbcType=INTEGER}
  </update>
  <update id="updateByPrimaryKeyWithBLOBs" parameterType="com.comdosoft.financial.manage.domain.zhangfu.Terminal" >
    <!--
      WARNING - @mbggenerated
      This element is automatically generated by MyBatis Generator, do not modify.
      This element was generated on Thu Jan 29 14:34:31 CST 2015.
    -->
    update terminals
    set good_id = #{goodId,jdbcType=INTEGER},
      serial_num = #{serialNum,jdbcType=VARCHAR},
      pay_channel_id = #{payChannelId,jdbcType=INTEGER},
      merchant_id = #{merchantId,jdbcType=INTEGER},
      customer_id = #{customerId,jdbcType=INTEGER},
      status = #{status,jdbcType=TINYINT},
      agent_id = #{agentId,jdbcType=INTEGER},
      order_id = #{orderId,jdbcType=INTEGER},
      account = #{account,jdbcType=VARCHAR},
      password = #{password,jdbcType=VARCHAR},
      is_return_cs_depots = #{isReturnCsDepots,jdbcType=BIT},
      created_at = #{createdAt,jdbcType=TIMESTAMP},
      updated_at = #{updatedAt,jdbcType=TIMESTAMP},
      type = #{type,jdbcType=TINYINT},
      merchant_num = #{merchantNum,jdbcType=VARCHAR},
      is_rate_wrong = #{isRateWrong,jdbcType=BIT},
      base_rate = #{baseRate,jdbcType=INTEGER},
      terminal_marks_id = #{terminalMarksId,jdbcType=INTEGER},
      billing_cycles_id = #{billingCyclesId,jdbcType=INTEGER},
      mark_xml = #{markXml,jdbcType=LONGVARCHAR}
    where id = #{id,jdbcType=INTEGER}
  </update>
  <update id="updateByPrimaryKey" parameterType="com.comdosoft.financial.manage.domain.zhangfu.Terminal" >
    <!--
      WARNING - @mbggenerated
      This element is automatically generated by MyBatis Generator, do not modify.
      This element was generated on Thu Jan 29 14:34:31 CST 2015.
    -->
    update terminals
    set good_id = #{goodId,jdbcType=INTEGER},
      serial_num = #{serialNum,jdbcType=VARCHAR},
      pay_channel_id = #{payChannelId,jdbcType=INTEGER},
      merchant_id = #{merchantId,jdbcType=INTEGER},
      customer_id = #{customerId,jdbcType=INTEGER},
      status = #{status,jdbcType=TINYINT},
      agent_id = #{agentId,jdbcType=INTEGER},
      order_id = #{orderId,jdbcType=INTEGER},
      account = #{account,jdbcType=VARCHAR},
      password = #{password,jdbcType=VARCHAR},
      is_return_cs_depots = #{isReturnCsDepots,jdbcType=BIT},
      created_at = #{createdAt,jdbcType=TIMESTAMP},
      updated_at = #{updatedAt,jdbcType=TIMESTAMP},
      type = #{type,jdbcType=TINYINT},
      merchant_num = #{merchantNum,jdbcType=VARCHAR},
      is_rate_wrong = #{isRateWrong,jdbcType=BIT},
      base_rate = #{baseRate,jdbcType=INTEGER},
      terminal_marks_id = #{terminalMarksId,jdbcType=INTEGER},
      billing_cycles_id = #{billingCyclesId,jdbcType=INTEGER}
    where id = #{id,jdbcType=INTEGER}
  </update>
</mapper>