<?xml version="1.0" encoding="UTF-8" ?>
<!DOCTYPE mapper PUBLIC "-//mybatis.org//DTD Mapper 3.0//EN" "http://mybatis.org/dtd/mybatis-3-mapper.dtd" >
<mapper namespace="com.comdosoft.financial.manage.mapper.trades.TradeRecordMapper" >
  <resultMap id="BaseResultMap" type="com.comdosoft.financial.manage.domain.trades.TradeRecord" >
    <!--
      WARNING - @mbggenerated
      This element is automatically generated by MyBatis Generator, do not modify.
    -->
    <id column="id" property="id" jdbcType="INTEGER" />
    <result column="trade_number" property="tradeNumber" jdbcType="VARCHAR" />
    <result column="batch_number" property="batchNumber" jdbcType="VARCHAR" />
    <result column="terminal_number" property="terminalNumber" jdbcType="VARCHAR" />
    <result column="order_number" property="orderNumber" jdbcType="VARCHAR" />
    <result column="agent_id" property="agentId" jdbcType="INTEGER" />
    <result column="merchant_number" property="merchantNumber" jdbcType="VARCHAR" />
    <result column="pay_channel_id" property="payChannelId" jdbcType="INTEGER" />
    <result column="profit_price" property="profitPrice" jdbcType="INTEGER" />
    <result column="amount" property="amount" jdbcType="INTEGER" />
    <result column="poundage" property="poundage" jdbcType="INTEGER" />
    <result column="traded_at" property="tradedAt" jdbcType="TIMESTAMP" />
    <result column="sys_order_id" property="sysOrderId" jdbcType="INTEGER" />
    <result column="account_number" property="accountNumber" jdbcType="VARCHAR" />
    <result column="account_name" property="accountName" jdbcType="VARCHAR" />
    <result column="actual_payment_price" property="actualPaymentPrice" jdbcType="INTEGER" />
    <result column="paid_result" property="paidResult" jdbcType="TINYINT" />
    <result column="paid_code" property="paidCode" jdbcType="INTEGER" />
    <result column="paid_error_description" property="paidErrorDescription" jdbcType="VARCHAR" />
    <result column="created_at" property="createdAt" jdbcType="TIMESTAMP" />
    <result column="updated_at" property="updatedAt" jdbcType="TIMESTAMP" />
    <result column="trade_type_id" property="tradeTypeId" jdbcType="INTEGER" />
    <result column="traded_status" property="tradedStatus" jdbcType="INTEGER" />
    <result column="attach_status" property="attachStatus" jdbcType="INTEGER" />
  </resultMap>
  <delete id="deleteByPrimaryKey" parameterType="java.lang.Integer" >
    <!--
      WARNING - @mbggenerated
      This element is automatically generated by MyBatis Generator, do not modify.
    -->
    delete from trade_records
    where id = #{id,jdbcType=INTEGER}
  </delete>
  <insert id="insert" parameterType="com.comdosoft.financial.manage.domain.trades.TradeRecord" >
    <!--
      WARNING - @mbggenerated
      This element is automatically generated by MyBatis Generator, do not modify.
    -->
    insert into trade_records (id, trade_number, batch_number, 
      terminal_number, order_number, agent_id, 
      merchant_number, pay_channel_id, profit_price, 
      amount, poundage, traded_at, 
      sys_order_id, account_number, account_name, 
      actual_payment_price, paid_result, paid_code, 
      paid_error_description, created_at, updated_at, 
      trade_type_id, traded_status, attach_status
      )
    values (#{id,jdbcType=INTEGER}, #{tradeNumber,jdbcType=VARCHAR}, #{batchNumber,jdbcType=VARCHAR}, 
      #{terminalNumber,jdbcType=VARCHAR}, #{orderNumber,jdbcType=VARCHAR}, #{agentId,jdbcType=INTEGER}, 
      #{merchantNumber,jdbcType=VARCHAR}, #{payChannelId,jdbcType=INTEGER}, #{profitPrice,jdbcType=INTEGER}, 
      #{amount,jdbcType=INTEGER}, #{poundage,jdbcType=INTEGER}, #{tradedAt,jdbcType=TIMESTAMP}, 
      #{sysOrderId,jdbcType=INTEGER}, #{accountNumber,jdbcType=VARCHAR}, #{accountName,jdbcType=VARCHAR}, 
      #{actualPaymentPrice,jdbcType=INTEGER}, #{paidResult,jdbcType=TINYINT}, #{paidCode,jdbcType=INTEGER}, 
      #{paidErrorDescription,jdbcType=VARCHAR}, #{createdAt,jdbcType=TIMESTAMP}, #{updatedAt,jdbcType=TIMESTAMP}, 
      #{tradeTypeId,jdbcType=INTEGER}, #{tradedStatus,jdbcType=INTEGER}, #{attachStatus,jdbcType=INTEGER}
      )
  </insert>
  <update id="updateByPrimaryKey" parameterType="com.comdosoft.financial.manage.domain.trades.TradeRecord" >
    <!--
      WARNING - @mbggenerated
      This element is automatically generated by MyBatis Generator, do not modify.
    -->
    update trade_records
    set trade_number = #{tradeNumber,jdbcType=VARCHAR},
      batch_number = #{batchNumber,jdbcType=VARCHAR},
      terminal_number = #{terminalNumber,jdbcType=VARCHAR},
      order_number = #{orderNumber,jdbcType=VARCHAR},
      agent_id = #{agentId,jdbcType=INTEGER},
      merchant_number = #{merchantNumber,jdbcType=VARCHAR},
      pay_channel_id = #{payChannelId,jdbcType=INTEGER},
      profit_price = #{profitPrice,jdbcType=INTEGER},
      amount = #{amount,jdbcType=INTEGER},
      poundage = #{poundage,jdbcType=INTEGER},
      traded_at = #{tradedAt,jdbcType=TIMESTAMP},
      sys_order_id = #{sysOrderId,jdbcType=INTEGER},
      account_number = #{accountNumber,jdbcType=VARCHAR},
      account_name = #{accountName,jdbcType=VARCHAR},
      actual_payment_price = #{actualPaymentPrice,jdbcType=INTEGER},
      paid_result = #{paidResult,jdbcType=TINYINT},
      paid_code = #{paidCode,jdbcType=INTEGER},
      paid_error_description = #{paidErrorDescription,jdbcType=VARCHAR},
      created_at = #{createdAt,jdbcType=TIMESTAMP},
      updated_at = #{updatedAt,jdbcType=TIMESTAMP},
      trade_type_id = #{tradeTypeId,jdbcType=INTEGER},
      traded_status = #{tradedStatus,jdbcType=INTEGER},
      attach_status = #{attachStatus,jdbcType=INTEGER}
    where id = #{id,jdbcType=INTEGER}
  </update>
  <select id="selectByPrimaryKey" resultMap="BaseResultMap" parameterType="java.lang.Integer" >
    <!--
      WARNING - @mbggenerated
      This element is automatically generated by MyBatis Generator, do not modify.
    -->
    select id, trade_number, batch_number, terminal_number, order_number, agent_id, merchant_number, 
    pay_channel_id, profit_price, amount, poundage, traded_at, sys_order_id, account_number, 
    account_name, actual_payment_price, paid_result, paid_code, paid_error_description, 
    created_at, updated_at, trade_type_id, traded_status, attach_status
    from trade_records
    where id = #{id,jdbcType=INTEGER}
  </select>
  <select id="selectAll" resultMap="BaseResultMap" >
    <!--
      WARNING - @mbggenerated
      This element is automatically generated by MyBatis Generator, do not modify.
    -->
    select id, trade_number, batch_number, terminal_number, order_number, agent_id, merchant_number, 
    pay_channel_id, profit_price, amount, poundage, traded_at, sys_order_id, account_number, 
    account_name, actual_payment_price, paid_result, paid_code, paid_error_description, 
    created_at, updated_at, trade_type_id, traded_status, attach_status
    from trade_records
  </select>
</mapper>